korax/__init__.py
korax/chatbot.py
korax-0.1.dist-info/LICENSE
korax-0.1.dist-info/METADATA
korax-0.1.dist-info/WHEEL
korax-0.1.dist-info/top_level.txt
korax-0.1.dist-info/RECORD
